xinject/__init__.py
xinject/_private/__init__.py
xinject/_private/classproperty.py
xinject/context.py
xinject/dependency.py
xinject/errors.py
xinject/proxy.py
xinject/pytest_plugin.py
xinject-1.5.0.dist-info/METADATA
xinject-1.5.0.dist-info/WHEEL
xinject-1.5.0.dist-info/entry_points.txt
xinject-1.5.0.dist-info/licenses/LICENSE
xinject-1.5.0.dist-info/RECORD
