Metadata-Version: 2.4
Name: xinject
Version: 1.5.0
Summary: Lazy dependency injection.
License-File: LICENSE
Keywords: dependency,injection,lazy,resource
Author: Josh Orr
Author-email: josh@orr.blue
Requires-Python: >=3.12,<4.0
Classifier: License :: OSI Approved :: The Unlicense (Unlicense)
Classifier: Programming Language :: Python :: 3
Classifier: Programming Language :: Python :: 3.12
Classifier: Programming Language :: Python :: 3.13
Classifier: Programming Language :: Python :: 3.14
Classifier: Topic :: Software Development :: Libraries :: Python Modules
Requires-Dist: xsentinels (>=1.2.0,<2.0.0)
Project-URL: Repository, https://github.com/xyngular/py-xinject
